statsdict/__init__.py
statsdict/py.typed
statsdict-0.1.8.dist-info/entry_points.txt
statsdict-0.1.8.dist-info/LICENSE.rst
statsdict-0.1.8.dist-info/WHEEL
statsdict-0.1.8.dist-info/METADATA
statsdict-0.1.8.dist-info/RECORD
