Metadata-Version: 2.1
Name: statsdict
Version: 0.1.8
Summary: Saveable dictionary of global stats
Home-page: https://github.com/hydrationdynamics/statsdict
License: BSD-3-Clause
Keywords: statistics
Author: Joel Berendzen
Author-email: joel@generisbio.com
Requires-Python: >=3.8.0,<4.0.0
Classifier: Development Status :: 4 - Beta
Classifier: Environment :: Console
Classifier: Intended Audience :: Science/Research
Classifier: License :: OSI Approved :: BSD License
Classifier: Natural Language :: English
Classifier: Operating System :: OS Independent
Classifier: Programming Language :: Python :: 3
Classifier: Programming Language :: Python :: 3.8
Classifier: Programming Language :: Python :: 3.9
Classifier: Programming Language :: Python :: 3.10
Classifier: Programming Language :: Python :: 3.11
Classifier: Programming Language :: Python :: 3.10
Classifier: Programming Language :: Python :: 3.11
Classifier: Programming Language :: Python :: 3.9
Classifier: Topic :: Scientific/Engineering :: Chemistry
Requires-Dist: Pint (>=0.19.2)
Requires-Dist: attrs (>=21.4.0)
Requires-Dist: loguru (>=0.6.0)
Requires-Dist: tabulate (>=0.8.9)
Requires-Dist: typer (>=0.4.1)
Requires-Dist: uncertainties (>=3.1.6)
Project-URL: Changelog, https://github.com/joelb123/statsdict/releases
Project-URL: Documentation, https://statsdict.readthedocs.io
Project-URL: Repository, https://github.com/hydrationdynamics/statsdict
